docs/agent_hocon_reference.md
docs/clients.md
docs/llm_info_hocon_reference.md
docs/manifest_hocon_reference.md
docs/mcp_service.md
docs/test_case_hocon_reference.md
docs/tests.md
docs/toolbox_info_hocon_reference.md
neuro_san/__init__.py
neuro_san/api/__init__.py
neuro_san/api/grpc/__init__.py
neuro_san/api/grpc/agent.proto
neuro_san/api/grpc/agent_pb2.py
neuro_san/api/grpc/agent_pb2_grpc.py
neuro_san/api/grpc/agent_service.json
neuro_san/api/grpc/chat.proto
neuro_san/api/grpc/chat_pb2.py
neuro_san/api/grpc/chat_pb2_grpc.py
neuro_san/api/grpc/concierge.proto
neuro_san/api/grpc/concierge_pb2.py
neuro_san/api/grpc/concierge_pb2_grpc.py
neuro_san/api/grpc/mime_data.proto
neuro_san/api/grpc/mime_data_pb2.py
neuro_san/api/grpc/mime_data_pb2_grpc.py
neuro_san/api/grpc/google/api/annotations.proto
neuro_san/api/grpc/google/api/http.proto
neuro_san/api/scripts/check_openapi_plugin.sh
neuro_san/api/scripts/convert_yaml_to_json.sh
neuro_san/api/scripts/do_generate.sh
neuro_san/api/scripts/protobuf_manifest.txt
neuro_san/client/__init__.py
neuro_san/client/agent_cli.py
neuro_san/client/agent_session_factory.py
neuro_san/client/concierge_session_factory.py
neuro_san/client/direct_agent_session_factory.py
neuro_san/client/direct_agent_storage_util.py
neuro_san/client/simple_one_shot.py
neuro_san/client/streaming_input_processor.py
neuro_san/client/thinking_file_message_processor.py
neuro_san/coded_tools/__init__.py
neuro_san/coded_tools/accountant.py
neuro_san/coded_tools/get_current_date_time.py
neuro_san/coded_tools/copy_cat/__init__.py
neuro_san/coded_tools/copy_cat/copyist.py
neuro_san/coded_tools/date_time/date_time.py
neuro_san/coded_tools/deep/__init__.py
neuro_san/coded_tools/deep/math_guy/__init__.py
neuro_san/coded_tools/deep/math_guy/calculator.py
neuro_san/coded_tools/math_guy/__init__.py
neuro_san/coded_tools/math_guy/async_closeable.py
neuro_san/coded_tools/math_guy/calculator.py
neuro_san/coded_tools/math_guy/sync_closeable.py
neuro_san/deploy/Dockerfile
neuro_san-0.6.23.dist-info/licenses/LICENSE.txt
neuro_san-0.6.23.dist-info/METADATA
neuro_san-0.6.23.dist-info/WHEEL
neuro_san-0.6.23.dist-info/top_level.txt
neuro_san-0.6.23.dist-info/RECORD
