Metadata-Version: 2.4
Name: neuro-san
Version: 0.6.23
Summary: NeuroAI data-driven System for multi-Agent Networks - client, library and server
Author-email: Dan Fink <Daniel.Fink@cognizant.com>
License-Expression: Apache-2.0
Project-URL: Homepage, https://github.com/cognizant-ai-lab/neuro-san
Project-URL: Repository, https://github.com/cognizant-ai-lab/neuro-san
Project-URL: Documentation, https://github.com/cognizant-ai-lab/neuro-san#readme
Keywords: LLM,langchain,agent,multi-agent
Classifier: Programming Language :: Python :: 3
Classifier: Operating System :: OS Independent
Classifier: Development Status :: 3 - Alpha
Classifier: Intended Audience :: Developers
Requires-Python: >=3.10
License-File: LICENSE.txt
Requires-Dist: leaf-common>=1.2.32
Requires-Dist: leaf-server-common>=0.1.23
Requires-Dist: grpcio>=1.62.0
Requires-Dist: grpcio-health-checking>=1.62.0
Requires-Dist: grpcio-reflection>=1.62.0
Requires-Dist: grpcio-tools>=1.62.0
Requires-Dist: protobuf>=4.25.3
Requires-Dist: pyhocon>=0.3.60
Requires-Dist: pyOpenSSL>=24.0.0
Requires-Dist: boto3>=1.34.51
Requires-Dist: botocore>=1.34.51
Requires-Dist: idna>=3.6
Requires-Dist: urllib3>=1.26.18
Requires-Dist: aiohttp<4.0,>=3.13.0
Requires-Dist: ruamel.yaml>=0.18.6
Requires-Dist: hvac>=1.1.0
Requires-Dist: langchain<2.0,>=1.2.0
Requires-Dist: langchain-core<2.0,>=1.2.5
Requires-Dist: langchain-classic<2.0,>=1.0.0
Requires-Dist: langchain-community<1.0,>=0.4
Requires-Dist: openai<2.0,>=1.54.1
Requires-Dist: bs4<0.1,>=0.0.2
Requires-Dist: pydantic<3.0,>=2.9.2
Requires-Dist: langchain-openai<2.0,>=1.0.0
Requires-Dist: httpx>=0.28.1
Requires-Dist: psutil>=7.0.0
Requires-Dist: tornado>=6.4.2
Requires-Dist: jsonschema>=4.19.0
Requires-Dist: janus>=2.0.0
Requires-Dist: watchdog>=6.0.0
Requires-Dist: validators>=0.22.0
Requires-Dist: timedinput>=0.1.1
Requires-Dist: json-repair<1.0,>=0.47.3
Requires-Dist: langchain-mcp-adapters<1.0,>=0.1.7
Dynamic: license-file
